[{"model":"main_app.invoice","pk":1,"fields":{"date":"2017-01-26","number":1,"issuer":1,"receiver":2}},
{"model":"main_app.invoice","pk":2,"fields":{"date":"2017-09-03","number":2,"issuer":12,"receiver":5}},
{"model":"main_app.invoice","pk":3,"fields":{"date":"2017-12-10","number":3,"issuer":4,"receiver":5}},
{"model":"main_app.invoice","pk":4,"fields":{"date":"2017-12-21","number":4,"issuer":4,"receiver":7}},
{"model":"main_app.invoice","pk":5,"fields":{"date":"2017-11-29","number":5,"issuer":15,"receiver":14}},
{"model":"main_app.invoice","pk":6,"fields":{"date":"2017-11-29","number":6,"issuer":6,"receiver":12}},
{"model":"main_app.invoice","pk":7,"fields":{"date":"2017-09-20","number":7,"issuer":14,"receiver":4}},
{"model":"main_app.invoice","pk":8,"fields":{"date":"2017-12-05","number":8,"issuer":12,"receiver":2}},
{"model":"main_app.invoice","pk":9,"fields":{"date":"2017-04-23","number":9,"issuer":2,"receiver":3}},
{"model":"main_app.invoice","pk":10,"fields":{"date":"2017-08-15","number":10,"issuer":12,"receiver":8}},
{"model":"main_app.invoice","pk":11,"fields":{"date":"2017-12-14","number":11,"issuer":9,"receiver":2}},
{"model":"main_app.invoice","pk":12,"fields":{"date":"2017-11-04","number":12,"issuer":14,"receiver":3}},
{"model":"main_app.invoice","pk":13,"fields":{"date":"2017-05-04","number":13,"issuer":13,"receiver":2}},
{"model":"main_app.invoice","pk":14,"fields":{"date":"2017-01-19","number":14,"issuer":7,"receiver":11}},
{"model":"main_app.invoice","pk":15,"fields":{"date":"2017-04-12","number":15,"issuer":6,"receiver":7}},
{"model":"main_app.invoice","pk":16,"fields":{"date":"2017-07-08","number":16,"issuer":8,"receiver":1}},
{"model":"main_app.invoice","pk":17,"fields":{"date":"2017-05-31","number":17,"issuer":11,"receiver":15}},
{"model":"main_app.invoice","pk":18,"fields":{"date":"2017-01-06","number":18,"issuer":13,"receiver":2}},
{"model":"main_app.invoice","pk":19,"fields":{"date":"2017-07-20","number":19,"issuer":12,"receiver":11}},
{"model":"main_app.invoice","pk":20,"fields":{"date":"2017-02-13","number":20,"issuer":4,"receiver":9}},
{"model":"main_app.invoice","pk":21,"fields":{"date":"2017-06-20","number":21,"issuer":15,"receiver":3}},
{"model":"main_app.invoice","pk":22,"fields":{"date":"2017-11-28","number":22,"issuer":9,"receiver":7}},
{"model":"main_app.invoice","pk":23,"fields":{"date":"2017-12-24","number":23,"issuer":10,"receiver":16}},
{"model":"main_app.invoice","pk":24,"fields":{"date":"2017-08-11","number":24,"issuer":6,"receiver":14}},
{"model":"main_app.invoice","pk":25,"fields":{"date":"2017-02-18","number":25,"issuer":13,"receiver":16}},
{"model":"main_app.invoice","pk":26,"fields":{"date":"2017-07-05","number":26,"issuer":8,"receiver":1}},
{"model":"main_app.invoice","pk":27,"fields":{"date":"2017-02-20","number":27,"issuer":15,"receiver":1}},
{"model":"main_app.invoice","pk":28,"fields":{"date":"2017-07-11","number":28,"issuer":7,"receiver":13}},
{"model":"main_app.invoice","pk":29,"fields":{"date":"2017-03-02","number":29,"issuer":15,"receiver":16}},
{"model":"main_app.invoice","pk":30,"fields":{"date":"2017-09-26","number":30,"issuer":16,"receiver":2}},
{"model":"main_app.invoice","pk":31,"fields":{"date":"2017-06-07","number":31,"issuer":1,"receiver":16}},
{"model":"main_app.invoice","pk":32,"fields":{"date":"2017-05-30","number":32,"issuer":4,"receiver":2}},
{"model":"main_app.invoice","pk":33,"fields":{"date":"2017-09-01","number":33,"issuer":11,"receiver":1}},
{"model":"main_app.invoice","pk":34,"fields":{"date":"2017-07-24","number":34,"issuer":7,"receiver":16}},
{"model":"main_app.invoice","pk":35,"fields":{"date":"2017-11-05","number":35,"issuer":11,"receiver":14}},
{"model":"main_app.invoice","pk":36,"fields":{"date":"2017-07-25","number":36,"issuer":9,"receiver":4}},
{"model":"main_app.invoice","pk":37,"fields":{"date":"2017-09-08","number":37,"issuer":2,"receiver":13}},
{"model":"main_app.invoice","pk":38,"fields":{"date":"2017-09-04","number":38,"issuer":14,"receiver":16}},
{"model":"main_app.invoice","pk":39,"fields":{"date":"2017-06-10","number":39,"issuer":10,"receiver":13}},
{"model":"main_app.invoice","pk":40,"fields":{"date":"2017-07-19","number":40,"issuer":14,"receiver":4}},
{"model":"main_app.invoice","pk":41,"fields":{"date":"2017-10-19","number":41,"issuer":3,"receiver":9}},
{"model":"main_app.invoice","pk":42,"fields":{"date":"2017-04-11","number":42,"issuer":9,"receiver":14}},
{"model":"main_app.invoice","pk":43,"fields":{"date":"2017-05-02","number":43,"issuer":5,"receiver":6}},
{"model":"main_app.invoice","pk":44,"fields":{"date":"2017-07-20","number":44,"issuer":6,"receiver":10}},
{"model":"main_app.invoice","pk":45,"fields":{"date":"2017-02-27","number":45,"issuer":4,"receiver":3}},
{"model":"main_app.invoice","pk":46,"fields":{"date":"2017-09-22","number":46,"issuer":8,"receiver":13}},
{"model":"main_app.invoice","pk":47,"fields":{"date":"2017-07-03","number":47,"issuer":13,"receiver":16}},
{"model":"main_app.invoice","pk":48,"fields":{"date":"2017-08-29","number":48,"issuer":4,"receiver":6}},
{"model":"main_app.invoice","pk":49,"fields":{"date":"2017-02-12","number":49,"issuer":15,"receiver":16}},
{"model":"main_app.invoice","pk":50,"fields":{"date":"2017-12-21","number":50,"issuer":14,"receiver":3}},
{"model":"main_app.invoice","pk":51,"fields":{"date":"2017-05-23","number":51,"issuer":13,"receiver":12}},
{"model":"main_app.invoice","pk":52,"fields":{"date":"2017-09-18","number":52,"issuer":8,"receiver":15}},
{"model":"main_app.invoice","pk":53,"fields":{"date":"2017-08-12","number":53,"issuer":10,"receiver":9}},
{"model":"main_app.invoice","pk":54,"fields":{"date":"2017-04-23","number":54,"issuer":16,"receiver":15}},
{"model":"main_app.invoice","pk":55,"fields":{"date":"2017-06-21","number":55,"issuer":12,"receiver":15}},
{"model":"main_app.invoice","pk":56,"fields":{"date":"2017-02-03","number":56,"issuer":3,"receiver":10}},
{"model":"main_app.invoice","pk":57,"fields":{"date":"2017-12-18","number":57,"issuer":4,"receiver":8}},
{"model":"main_app.invoice","pk":58,"fields":{"date":"2017-08-18","number":58,"issuer":6,"receiver":15}},
{"model":"main_app.invoice","pk":59,"fields":{"date":"2017-12-20","number":59,"issuer":7,"receiver":13}},
{"model":"main_app.invoice","pk":60,"fields":{"date":"2017-12-24","number":60,"issuer":15,"receiver":6}},
{"model":"main_app.invoice","pk":61,"fields":{"date":"2017-02-18","number":61,"issuer":15,"receiver":8}},
{"model":"main_app.invoice","pk":62,"fields":{"date":"2017-10-28","number":62,"issuer":3,"receiver":4}},
{"model":"main_app.invoice","pk":63,"fields":{"date":"2017-08-22","number":63,"issuer":10,"receiver":9}},
{"model":"main_app.invoice","pk":64,"fields":{"date":"2017-09-04","number":64,"issuer":2,"receiver":3}}]